browsergym/webarena/__init__.py
browsergym/webarena/config.py
browsergym/webarena/instance.py
browsergym/webarena/task.py
browsergym_webarena-0.14.3.dist-info/METADATA
browsergym_webarena-0.14.3.dist-info/WHEEL
browsergym_webarena-0.14.3.dist-info/RECORD
